airflow_ad_query/__init__.py
airflow_ad_query/ad_query.py
airflow_ad_query/ad_query_view.py
airflow_ad_query/commons.py
airflow_ad_query/test.py
airflow_ad_query/utils.py
airflow_ad_query/static/ace.js
airflow_ad_query/static/dataTables.bootstrap.css
airflow_ad_query/static/head.heml
airflow_ad_query/static/jquery.dataTables.css
airflow_ad_query/static/jquery.dataTables.min.js
airflow_ad_query/static/loading.gif
airflow_ad_query/static/main.css
airflow_ad_query/static/mode-sql.js
airflow_ad_query/static/sort_asc.png
airflow_ad_query/static/sort_both.png
airflow_ad_query/static/sort_desc.png
airflow_ad_query/static/theme-clouds.js
airflow_ad_query/static/theme-crimson_editor.js
airflow_ad_query/static/theme-dracula.js
airflow_ad_query/static/theme-one_dark.js
airflow_ad_query/static/theme-solarized_light.js
airflow_ad_query/static/theme-sqlserver.js
airflow_ad_query/static/theme-terminal.js
airflow_ad_query/static/theme-textmate.js
airflow_ad_query/static/theme-twilight.js
airflow_ad_query/static/theme-xcode.js
airflow_ad_query/templates/__init__.py
airflow_ad_query/templates/query.html
airflow_ad_query-0.1.1.dist-info/LICENSE
airflow_ad_query-0.1.1.dist-info/METADATA
airflow_ad_query-0.1.1.dist-info/WHEEL
airflow_ad_query-0.1.1.dist-info/entry_points.txt
airflow_ad_query-0.1.1.dist-info/top_level.txt
airflow_ad_query-0.1.1.dist-info/RECORD
