Metadata-Version: 2.1
Name: airflow-ad-query
Version: 0.1.1
Summary: airflow ad query
Home-page: https://github.com/wanlce/airflow-ad-query
Author: wano
Author-email: whox@foxmail.com
License: Apahce
License-File: LICENSE
Requires-Dist: apache-airflow (>=2.0.0)
Requires-Dist: WTForms (>=2.3.3)
